codesters/__init__.py
codesters/backgrounds.json
codesters/bezier.py
codesters/display_object.py
codesters/environment.py
codesters/execute.py
codesters/hitbox.py
codesters/manager.py
codesters/run.py
codesters/shapes.py
codesters/sprite.py
codesters/sprites.json
codesters/transformations.py
codesters/update-sprites.py
codesters/examples/basketball.py
codesters/examples/chainreaction.py
codesters/examples/feedthefish.py
codesters/examples/flappyfox.py
codesters/examples/flowerfox.py
codesters/examples/recycle.py
codesters/examples/wip/frogger.py
codesters/examples/wip/pictionary.py
codesters/examples/wip/quickbaseball.py
codesters/examples/wip/spaceinvaders.py
codesters/examples/wip/starhedgehog.py
codesters/examples/wip/tester.py
codesters/examples/wip/trianglebasketball.py
codesters/examples/wip/volleyball.py
codesters/sprites/111_-_ONLINE_ADVERSTISING.png
codesters/sprites/11d802cedaca453cba52ca500dce4b32.png
codesters/sprites/1478_-_Mail_2.png
codesters/sprites/1479_-_Weather.png
codesters/sprites/1480_-_Games.png
codesters/sprites/1481_-_Books.png
codesters/sprites/171_-_Message_Bubble_with_dots.png
codesters/sprites/173_-_Cloud.png
codesters/sprites/2.png
codesters/sprites/30_-_Reception_desk_1080px.jpg
codesters/sprites/4008791f51b742c1b94996f1ea0360e7.png
codesters/sprites/439_-_Browser.png
codesters/sprites/440_-_Calculator.png
codesters/sprites/441_-_Calendar.png
codesters/sprites/442_-_Camera.png
codesters/sprites/444_-_Contacts.png
codesters/sprites/455_-_Gallery.png
codesters/sprites/461_-_Maps.png
codesters/sprites/8984ff6668dc4437a4e32b210d7dfea3.png
codesters/sprites/African_American_Male_Doctor.G16.shadowless.2k.png
codesters/sprites/Alabama.png
codesters/sprites/Alaska.png
codesters/sprites/Alien-1.png
codesters/sprites/Alien-2.png
codesters/sprites/Alien1_outerspacemask-resize.png
codesters/sprites/Amusement_Park_2.png
codesters/sprites/Angel_Fish.png
codesters/sprites/Animal_Cell.F15.shadowless.2k.png
codesters/sprites/Arizona.png
codesters3-1.1.2.dist-info/AUTHORS
codesters3-1.1.2.dist-info/LICENSE
codesters3-1.1.2.dist-info/METADATA
codesters3-1.1.2.dist-info/WHEEL
codesters3-1.1.2.dist-info/entry_points.txt
codesters3-1.1.2.dist-info/top_level.txt
codesters3-1.1.2.dist-info/RECORD
