Metadata-Version: 2.1
Name: codesters3
Version: 1.1.2
Summary: Offline replication of the graphics on codesters.com, updated for Python 3
Author-email: Codesters <thomas@codesters.org>, Joey Parrish <joey.parrish@gmail.com>
Maintainer-email: Joey Parrish <joey.parrish@gmail.com>
Project-URL: Homepage, https://github.com/joeyparrish/codesters-graphics
Project-URL: Issues, https://github.com/joeyparrish/codesters-graphics/issues
Classifier: Programming Language :: Python :: 3
Classifier: Operating System :: OS Independent
Classifier: License :: OSI Approved :: MIT License
Classifier: Intended Audience :: Education
Classifier: Topic :: Education :: Computer Aided Instruction (CAI)
Classifier: Development Status :: 2 - Pre-Alpha
Requires-Python: >=3.9
License-File: LICENSE
License-File: AUTHORS
Requires-Dist: Pillow<11,>=10
